Workbook

Sheet Fundraising Roadmap
B2: Instructions: | C2: Only Update cells in YELLOW. | G2: Total Supply | H2: 1000000000 | I2: $YMTA
B3: We can help updating the structure of the spreadsheet, if more or less rounds are part of the Fundraising strategy
B5: Yamata Fundraising Roadmap | J5: Key Figures at a Glance
D6: 46023 | E6: 46054 | F6: Later | K6: Tokens | L6: $ | M6: Token Allocation %
D7: Pre Sale | E7: Node Sale | F7: Public Sale | J7: Total Raise | K7: =SUM(C13:H13) -> 120000000 | L7: =SUM(C14:H16) -> 4100000 | M7: =SUM(C9:H9) -> 0.12
B8: Instrument | D8: Equity + Token Warrant (1:1) | E8: NFTs | F8: Tokens | J8: Privately | K8: =SUM(C12,D12,F12) -> 0 | L8: =SUM(C14,D14,F14) -> 1000000 | M8: =SUM(C9:E9) -> 0.1
B9: % Sold | D9: 0.1 | F9: 0.02 | J9: Publicly | K9: =SUM(E12) -> 50000 | L9: =SUM(E15:F16) -> 3100000 | M9: =SUM(F9) -> 0.02
B10: Price | D10: 0.02 | E10: 42 | F10: 0.05
B11: Price Delta | D11: - | E11: - | F11: - | J11: Multiple Analysis
B12: Nodes Sold | E12: 50000 | J12: PreSeed to Public | K12: =F10/D10 -> 2.5
B13: Tokens Sold | D13: =$H$2*D9 -> 100000000 | F13: =$H$2*F9 -> 20000000
B14: Equity Raise | D14: =D18*D9 -> 1000000 | E14: - | F14: -
B15: Node Raise | D15: - | E15: =E10*E12 -> 2100000 | F15: -
B16: Token Raise | D16: - | E16: - | F16: =$H$2*F9*F10 -> 1000000
B17: FDV Valuation | D17: =$H$2*D10 -> 20000000 | E17: - | F17: =$H$2*F10 -> 50000000
B18: Post-Money Valuation | D18: =D17/2 -> 10000000 | E18: - | F18: -
B19: Vesting | D19: 20 mo | E19: 10 mo | F19: 0 mo
B20: Cliff | D20: 1 mo | E20: 2 mo | F20: 0 mo | J20: Private rounds | K20: =C9+F9+D9 -> 0.12 | L20: % can be adjusted dynamically between rounds
B21: Discount | D21: =iferror(1-(D17/$E$17),"") | J21: Public Rounds | K21: =SUM(E9) -> 0 | L21: % can be adjusted dynamically between rounds
B23: Floor | D23: 50000
B24: Ceiling | D24: 500000
B25: Max Checks | D25: =D14/D23 -> 20
B26: Avg Ticket | D26: 200000
B27: Avg Checks | D27: =D14/D26 -> 5
B28: Min Checks | D28: =D14/D24 -> 2

Sheet Token Allocation
H2: $YMTA | I2: Total Supply | J2: ='Fundraising Roadmap'!H2 -> 1000000000
B4: Yamata - Token Allocation
B5: Tranche | C5: Allocation % | D5: Tokens | E5: % Unlocked at TGE | F5: Tokens unlckd at TGE | G5: Cliff | H5: Vesting | I5: Total Length
B6: Public | C6: =C7 -> 0.02 | D6: =D7 -> 20000000 | E6: =SUMPRODUCT(C7,E7) -> 0.02 | F6: =F7 -> 20000000
B7: Public Sale | C7: {=iferror(INDEX('Fundraising Roadmap'!$B$7:$H$21,3,MATCH($B7,'Fundraising Roadmap'!$B$7:$H$7,0)),"")} -> 0.02 | D7: =$J$2*C7 -> 20000000 | E7: 1 | F7: =E7*D7 -> 20000000 | G7: 0 | H7: 0 | I7: =G7+H7 -> 0
B8: Community | C8: =SUM(C9:C12) -> 0.49 | D8: =SUM(D9:D12) -> 490000000 | E8: =SUMPRODUCT(C9:C12,E9:E12) -> 0.078 | F8: =SUM(F9:F12) -> 78000000
B9: Ecosystem | C9: 0.15 | D9: =$J$2*C9 -> 150000000 | E9: 0.2 | F9: =E9*D9 -> 30000000 | G9: 12 | H9: 48 | I9: =G9+H9 -> 60 | J9: =F9/sum(D9:D12) -> 0.06122449
B10: Marketing & Partnerships | C10: 0.12 | D10: =$J$2*C10 -> 120000000 | E10: 0.15 | F10: =E10*D10 -> 18000000 | G10: 0 | H10: 36 | I10: =SUM(G10:H10) -> 36
B11: Validator Nodes (VD) | C11: 0.2 | D11: =$J$2*C11 -> 200000000 | E11: 0.15 | F11: =E11*D11 -> 30000000 | G11: 0 | H11: 60 | I11: =SUM(G11:H11) -> 60
B12: Genesis Trader Program | C12: 0.02 | D12: =$J$2*C12 -> 20000000 | E12: 0 | F12: =E12*D12 -> 0 | G12: 0 | H12: 12 | I12: =SUM(G12:H12) -> 12
B13: Early Stage & Private Investments | C13: =SUM(C14:C16) -> 0.1 | D13: =SUM(D14:D18) -> 840000000 | E13: =SUMPRODUCT(C14:C18,E14:E18) -> 0.076 | F13: =sum(F14:F16) -> 10000000
B14: Pre Sale | C14: {=iferror(INDEX('Fundraising Roadmap'!$B$7:$H$21,3,MATCH($B14,'Fundraising Roadmap'!$B$7:$H$7,0)),"")} -> 0.1 | D14: =$J$2*C14 -> 100000000 | E14: 0.1 | F14: =E14*D14 -> 10000000 | G14: 1 | H14: 20 | I14: =SUM(G14:H14) -> 21
C15: {=iferror(INDEX('Fundraising Roadmap'!$B$7:$H$21,3,MATCH($B15,'Fundraising Roadmap'!$B$7:$H$7,0)),"")} | D15: =$J$2*C15 -> 0 | E15: 0.15 | F15: =E15*D15 -> 0 | I15: =SUM(G15:H15) -> 0
C16: {=iferror(INDEX('Fundraising Roadmap'!$B$7:$H$21,3,MATCH($B16,'Fundraising Roadmap'!$B$7:$H$7,0)),"")} | D16: =$J$2*C16 -> 0 | E16: 0.05 | F16: =E16*D16 -> 0 | I16: =SUM(G16:H16) -> 0
B17: Liquidity | C17: =SUM(C18:C20) -> 0.1 | D17: =SUM(D18:D24) -> 680000000 | E17: =SUMPRODUCT(C18:C24,E18:E24) -> 0.06 | F17: =sum(F18:F20) -> 60000000
B18: Market Makers | C18: 0.06 | D18: =$J$2*C18 -> 60000000 | E18: 1 | F18: =E18*D18 -> 60000000 | G18: 0 | H18: 0 | I18: =SUM(G18:H18) -> 0
B19: MM Incentive Program | C19: 0.04 | D19: =$J$2*C19 -> 40000000 | E19: 0 | F19: =E19*D19 -> 0 | G19: 0 | H19: 36
B21: Team, Advisors, Reserve | C21: =SUM(C22:C24) -> 0.29 | D21: =sum(D22:D24) -> 290000000 | E21: =SUMPRODUCT(C22:C24,E22:E24) -> 0 | F21: =sum(F22:F24) -> 0
B22: Foundation Reserve | C22: =1-SUM(C6,C8,C13,C17,C23,C24) -> 0.08 | D22: =$J$2*C22 -> 80000000 | E22: 0 | F22: =E22*D22 -> 0 | G22: 6 | H22: 36 | I22: =SUM(G22:H22) -> 42
B23: Advisors | C23: 0.04 | D23: =$J$2*C23 -> 40000000 | E23: 0 | F23: =E23*D23 -> 0 | G23: 12 | H23: 36 | I23: =SUM(G23:H23) -> 48
B24: Core Team | C24: 0.17 | D24: =$J$2*C24 -> 170000000 | E24: 0 | F24: =E24*D24 -> 0 | G24: 12 | H24: 36 | I24: =SUM(G24:H24) -> 48
B25: Total | C25: =sum(C6,C8,C13,C21,C17) -> 1 | D25: =sum(D6,D8,D13,D21) -> 1640000000 | E25: =F25/D25 -> 0.10243902 | F25: =sum(F6,F8,F13,F21,F17) -> 168000000

Sheet Token Release Schedule
C2: Yamata Token Release Schedule | U2: PRICE / MULTIPLE / CIRC MARKETCAP ANALYSIS
C3: Pre Sale | D3: Public Sale | F3: Core Team | G3: Advisors | H3: Foundation Reserve | I3: Marketing & Partnerships | J3: Validator Nodes (VD) | K3: Ecosystem | L3: Genesis Trader Program | M3: Market Makers | N3: MM Incentive Program | O3: TOTAL RELEASED | P3: EXTERNAL | Q3: CIRC SUPPLY | R3: CIRC % | S3: TOTAL SUPPLY ADDED INTO CIRC % | T3: INFLATION % | U3: ='Fundraising Roadmap'!$F$10*U4 -> 0.033 | V3: ='Fundraising Roadmap'!$F$10*V4 -> 0.05 | W3: ='Fundraising Roadmap'!$F$10*W4 -> 0.15 | X3: ='Fundraising Roadmap'!$F$10*X4 -> 0.25 | Y3: ='Fundraising Roadmap'!$F$10*Y4 -> 0.5 | Z3: ='Fundraising Roadmap'!$F$10*Z4 -> 1 | AA3: ='Fundraising Roadmap'!$F$10*AA4 -> 1.65 | AB3: ='Fundraising Roadmap'!$F$10*AB4 -> 2.5 | AC3: ='Fundraising Roadmap'!$F$10*AC4 -> 5
B4: % | C4: {=iferror(INDEX('Token Allocation'!$B$6:$J$26,MATCH(C$3,'Token Allocation'!$B$6:$B$26,0),2),"")} -> 0.1 | D4: {=iferror(INDEX('Token Allocation'!$B$6:$J$26,MATCH(D$3,'Token Allocation'!$B$6:$B$26,0),2),"")} -> 0.02 | E4: {=iferror(INDEX('Token Allocation'!$B$6:$J$26,MATCH(E$3,'Token Allocation'!$B$6:$B$26,0),2),"")} | F4: {=iferror(INDEX('Token Allocation'!$B$6:$J$26,MATCH(F$3,'Token Allocation'!$B$6:$B$26,0),2),"")} -> 0.17 | G4: {=iferror(INDEX('Token Allocation'!$B$6:$J$26,MATCH(G$3,'Token Allocation'!$B$6:$B$26,0),2),"")} -> 0.04 | H4: {=iferror(INDEX('Token Allocation'!$B$6:$J$26,MATCH(H$3,'Token Allocation'!$B$6:$B$26,0),2),"")} -> 0.08 | I4: {=iferror(INDEX('Token Allocation'!$B$6:$J$26,MATCH(I$3,'Token Allocation'!$B$6:$B$26,0),2),"")} -> 0.12 | J4: {=iferror(INDEX('Token Allocation'!$B$6:$J$26,MATCH(J$3,'Token Allocation'!$B$6:$B$26,0),2),"")} -> 0.2 | ... N4: {=iferror(INDEX('Token Allocation'!$B$6:$J$26,MATCH(N$3,'Token Allocation'!$B$6:$B$26,0),2),"")} -> 0.04 | O4: =SUM(C4:N4) -> 1 | T4: MULTIPLE Public | U4: 0.66 | V4: 1 | W4: 3 | X4: 5 | Y4: 10 | Z4: 20 | AA4: 33 | AB4: 50 | AC4: 100
B5: Total | C5: =IFERROR(C4*'Token Allocation'!$J$2,"") -> 100000000 | D5: =IFERROR(D4*'Token Allocation'!$J$2,"") -> 20000000 | E5: =IFERROR(E4*'Token Allocation'!$J$2,"") -> 0 | F5: =IFERROR(F4*'Token Allocation'!$J$2,"") -> 170000000 | G5: =IFERROR(G4*'Token Allocation'!$J$2,"") -> 40000000 | H5: =IFERROR(H4*'Token Allocation'!$J$2,"") -> 80000000 | I5: =IFERROR(I4*'Token Allocation'!$J$2,"") -> 120000000 | J5: =IFERROR(J4*'Token Allocation'!$J$2,"") -> 200000000 | ... N5: =IFERROR(N4*'Token Allocation'!$J$2,"") -> 40000000 | O5: =SUM(C5:N5) -> 1000000000 | T5: MULTIPLE Pre Sale | U5: ='Fundraising Roadmap'!$K$12*U4 -> 1.65 | V5: ='Fundraising Roadmap'!$K$12*V4 -> 2.5 | W5: ='Fundraising Roadmap'!$K$12*W4 -> 7.5 | X5: ='Fundraising Roadmap'!$K$12*X4 -> 12.5 | Y5: ='Fundraising Roadmap'!$K$12*Y4 -> 25 | Z5: ='Fundraising Roadmap'!$K$12*Z4 -> 50 | AA5: ='Fundraising Roadmap'!$K$12*AA4 -> 82.5 | AB5: ='Fundraising Roadmap'!$K$12*AB4 -> 125 | AC5: ='Fundraising Roadmap'!$K$12*AC4 -> 250
B6: Unlocked at TGE | C6: {=iferror(INDEX('Token Allocation'!$B$5:$J$26,MATCH(C$3,'Token Allocation'!$B$5:$B$26,0),5),"")} -> 10000000 | D6: {=iferror(INDEX('Token Allocation'!$B$5:$J$26,MATCH(D$3,'Token Allocation'!$B$5:$B$26,0),5),"")} -> 20000000 | E6: {=iferror(INDEX('Token Allocation'!$B$5:$J$26,MATCH(E$3,'Token Allocation'!$B$5:$B$26,0),5),"")} | F6: {=iferror(INDEX('Token Allocation'!$B$5:$J$26,MATCH(F$3,'Token Allocation'!$B$5:$B$26,0),5),"")} -> 0 | G6: {=iferror(INDEX('Token Allocation'!$B$5:$J$26,MATCH(G$3,'Token Allocation'!$B$5:$B$26,0),5),"")} -> 0 | H6: {=iferror(INDEX('Token Allocation'!$B$5:$J$26,MATCH(H$3,'Token Allocation'!$B$5:$B$26,0),5),"")} -> 0 | I6: {=iferror(INDEX('Token Allocation'!$B$5:$J$26,MATCH(I$3,'Token Allocation'!$B$5:$B$26,0),5),"")} -> 18000000 | J6: {=iferror(INDEX('Token Allocation'!$B$5:$J$26,MATCH(J$3,'Token Allocation'!$B$5:$B$26,0),5),"")} -> 30000000 | ... N6: {=iferror(INDEX('Token Allocation'!$B$5:$J$26,MATCH(N$3,'Token Allocation'!$B$5:$B$26,0),5),"")} -> 0 | O6: =SUM(C6:N6) -> 168000000
B7: Cliff | C7: {=iferror(INDEX('Token Allocation'!$B$5:$J$26,MATCH(C$3,'Token Allocation'!$B$5:$B$26,0),6),"")} -> 1 | D7: {=iferror(INDEX('Token Allocation'!$B$5:$J$26,MATCH(D$3,'Token Allocation'!$B$5:$B$26,0),6),"")} -> 0 | E7: {=iferror(INDEX('Token Allocation'!$B$5:$J$26,MATCH(E$3,'Token Allocation'!$B$5:$B$26,0),6),"")} | F7: {=iferror(INDEX('Token Allocation'!$B$5:$J$26,MATCH(F$3,'Token Allocation'!$B$5:$B$26,0),6),"")} -> 12 | G7: {=iferror(INDEX('Token Allocation'!$B$5:$J$26,MATCH(G$3,'Token Allocation'!$B$5:$B$26,0),6),"")} -> 12 | H7: {=iferror(INDEX('Token Allocation'!$B$5:$J$26,MATCH(H$3,'Token Allocation'!$B$5:$B$26,0),6),"")} -> 6 | I7: {=iferror(INDEX('Token Allocation'!$B$5:$J$26,MATCH(I$3,'Token Allocation'!$B$5:$B$26,0),6),"")} -> 0 | J7: {=iferror(INDEX('Token Allocation'!$B$5:$J$26,MATCH(J$3,'Token Allocation'!$B$5:$B$26,0),6),"")} -> 0 | ... N7: {=iferror(INDEX('Token Allocation'!$B$5:$J$26,MATCH(N$3,'Token Allocation'!$B$5:$B$26,0),6),"")} -> 0
B8: Vesting | C8: {=iferror(INDEX('Token Allocation'!$B$5:$J$26,MATCH(C$3,'Token Allocation'!$B$5:$B$26,0),7),"")} -> 20 | D8: {=iferror(INDEX('Token Allocation'!$B$5:$J$26,MATCH(D$3,'Token Allocation'!$B$5:$B$26,0),7),"")} -> 0 | E8: {=iferror(INDEX('Token Allocation'!$B$5:$J$26,MATCH(E$3,'Token Allocation'!$B$5:$B$26,0),7),"")} | F8: {=iferror(INDEX('Token Allocation'!$B$5:$J$26,MATCH(F$3,'Token Allocation'!$B$5:$B$26,0),7),"")} -> 36 | G8: {=iferror(INDEX('Token Allocation'!$B$5:$J$26,MATCH(G$3,'Token Allocation'!$B$5:$B$26,0),7),"")} -> 36 | H8: {=iferror(INDEX('Token Allocation'!$B$5:$J$26,MATCH(H$3,'Token Allocation'!$B$5:$B$26,0),7),"")} -> 36 | I8: {=iferror(INDEX('Token Allocation'!$B$5:$J$26,MATCH(I$3,'Token Allocation'!$B$5:$B$26,0),7),"")} -> 36 | J8: {=iferror(INDEX('Token Allocation'!$B$5:$J$26,MATCH(J$3,'Token Allocation'!$B$5:$B$26,0),7),"")} -> 60 | ... N8: {=iferror(INDEX('Token Allocation'!$B$5:$J$26,MATCH(N$3,'Token Allocation'!$B$5:$B$26,0),7),"")} -> 36
B9: 1 | C9: =if(C$7=0, if($B9=1, C$6, IF(and($B9>C$7,$B9<=sum(C$8,C$7)),(C$5-C$6)/(C$8-1),"")),IF($B9=1,C$6,IF(and($B9>C$7,$B9<=sum(C$8,C$7)),(C$5-C$6)/C$8,""))) -> 10000000 | D9: =if(D$7=0, if($B9=1, D$6, IF(and($B9>D$7,$B9<=sum(D$8,D$7)),(D$5-D$6)/(D$8-1),"")),IF($B9=1,D$6,IF(and($B9>D$7,$B9<=sum(D$8,D$7)),(D$5-D$6)/D$8,""))) -> 20000000 | E9: =if(E$7=0, if($B9=1, E$6, IF(and($B9>E$7,$B9<=sum(E$8,E$7)),(E$5-E$6)/(E$8-1),"")),IF($B9=1,E$6,IF(and($B9>E$7,$B9<=sum(E$8,E$7)),(E$5-E$6)/E$8,""))) | F9: =if(F$7=0, if($B9=1, F$6, IF(and($B9>F$7,$B9<=sum(F$8,F$7)),(F$5-F$6)/(F$8-1),"")),IF($B9=1,F$6,IF(and($B9>F$7,$B9<=sum(F$8,F$7)),(F$5-F$6)/F$8,""))) -> 0 | G9: =if(G$7=0, if($B9=1, G$6, IF(and($B9>G$7,$B9<=sum(G$8,G$7)),(G$5-G$6)/(G$8-1),"")),IF($B9=1,G$6,IF(and($B9>G$7,$B9<=sum(G$8,G$7)),(G$5-G$6)/G$8,""))) -> 0 | H9: =if(H$7=0, if($B9=1, H$6, IF(and($B9>H$7,$B9<=sum(H$8,H$7)),(H$5-H$6)/(H$8-1),"")),IF($B9=1,H$6,IF(and($B9>H$7,$B9<=sum(H$8,H$7)),(H$5-H$6)/H$8,""))) -> 0 | I9: =if(I$7=0, if($B9=1, I$6, IF(and($B9>I$7,$B9<=sum(I$8,I$7)),(I$5-I$6)/(I$8-1),"")),IF($B9=1,I$6,IF(and($B9>I$7,$B9<=sum(I$8,I$7)),(I$5-I$6)/I$8,""))) -> 18000000 | J9: =if(J$7=0, if($B9=1, J$6, IF(and($B9>J$7,$B9<=sum(J$8,J$7)),(J$5-J$6)/(J$8-1),"")),IF($B9=1,J$6,IF(and($B9>J$7,$B9<=sum(J$8,J$7)),(J$5-J$6)/J$8,""))) -> 30000000 | ... N9: =if(N$7=0, if($B9=1, N$6, IF(and($B9>N$7,$B9<=sum(N$8,N$7)),(N$5-N$6)/(N$8-1),"")),IF($B9=1,N$6,IF(and($B9>N$7,$B9<=sum(N$8,N$7)),(N$5-N$6)/N$8,""))) -> 0 | O9: =SUM(C9:N9) -> 168000000 | P9: =N9+SUM(E9:H9) -> 0 | Q9: =SUM(C9:N9) -> 168000000 | R9: =Q9/$O$5 -> 0.168 | U9: =$Q9*U$3 -> 5544000 | V9: =$Q9*V$3 -> 8400000 | W9: =$Q9*W$3 -> 25200000 | X9: =$Q9*X$3 -> 42000000 | Y9: =$Q9*Y$3 -> 84000000 | Z9: =$Q9*Z$3 -> 168000000 | AA9: =$Q9*AA$3 -> 277200000 | AB9: =$Q9*AB$3 -> 420000000 | AC9: =$Q9*AC$3 -> 840000000
B10: 2 | C10: =if(C$7=0, if($B10=1, C$6, IF(and($B10>C$7,$B10<=sum(C$8,C$7)),(C$5-C$6)/(C$8-1),"")),IF($B10=1,C$6,IF(and($B10>C$7,$B10<=sum(C$8,C$7)),(C$5-C$6)/C$8,""))) -> 4500000 | D10: =if(D$7=0, if($B10=1, D$6, IF(and($B10>D$7,$B10<=sum(D$8,D$7)),(D$5-D$6)/(D$8-1),"")),IF($B10=1,D$6,IF(and($B10>D$7,$B10<=sum(D$8,D$7)),(D$5-D$6)/D$8,""))) | E10: =if(E$7=0, if($B10=1, E$6, IF(and($B10>E$7,$B10<=sum(E$8,E$7)),(E$5-E$6)/(E$8-1),"")),IF($B10=1,E$6,IF(and($B10>E$7,$B10<=sum(E$8,E$7)),(E$5-E$6)/E$8,""))) | F10: =if(F$7=0, if($B10=1, F$6, IF(and($B10>F$7,$B10<=sum(F$8,F$7)),(F$5-F$6)/(F$8-1),"")),IF($B10=1,F$6,IF(and($B10>F$7,$B10<=sum(F$8,F$7)),(F$5-F$6)/F$8,""))) | G10: =if(G$7=0, if($B10=1, G$6, IF(and($B10>G$7,$B10<=sum(G$8,G$7)),(G$5-G$6)/(G$8-1),"")),IF($B10=1,G$6,IF(and($B10>G$7,$B10<=sum(G$8,G$7)),(G$5-G$6)/G$8,""))) | H10: =if(H$7=0, if($B10=1, H$6, IF(and($B10>H$7,$B10<=sum(H$8,H$7)),(H$5-H$6)/(H$8-1),"")),IF($B10=1,H$6,IF(and($B10>H$7,$B10<=sum(H$8,H$7)),(H$5-H$6)/H$8,""))) | I10: =if(I$7=0, if($B10=1, I$6, IF(and($B10>I$7,$B10<=sum(I$8,I$7)),(I$5-I$6)/(I$8-1),"")),IF($B10=1,I$6,IF(and($B10>I$7,$B10<=sum(I$8,I$7)),(I$5-I$6)/I$8,""))) -> 2914285.7 | J10: =if(J$7=0, if($B10=1, J$6, IF(and($B10>J$7,$B10<=sum(J$8,J$7)),(J$5-J$6)/(J$8-1),"")),IF($B10=1,J$6,IF(and($B10>J$7,$B10<=sum(J$8,J$7)),(J$5-J$6)/J$8,""))) -> 2881355.9 | ... N10: =if(N$7=0, if($B10=1, N$6, IF(and($B10>N$7,$B10<=sum(N$8,N$7)),(N$5-N$6)/(N$8-1),"")),IF($B10=1,N$6,IF(and($B10>N$7,$B10<=sum(N$8,N$7)),(N$5-N$6)/N$8,""))) -> 1142857.1 | O10: =SUM(C10:N10) -> 13256681 | P10: =N10+SUM(E10:H10) -> 1142857.1 | Q10: =Q9+SUM(C10:N10) -> 1.8125668e+08 | R10: =Q10/$O$5 -> 0.18125668 | S10: =R10-R9 -> 0.013256681 | T10: =(R10/R9)-100% -> 0.078908813 | U10: =$Q10*U$3 -> 5981470.5 | V10: =$Q10*V$3 -> 9062834 | W10: =$Q10*W$3 -> 27188502 | X10: =$Q10*X$3 -> 45314170 | Y10: =$Q10*Y$3 -> 90628340 | Z10: =$Q10*Z$3 -> 1.8125668e+08 | AA10: =$Q10*AA$3 -> 299073523 | AB10: =$Q10*AB$3 -> 4.531417e+08 | AC10: =$Q10*AC$3 -> 906283403
B11: 3 | C11: =if(C$7=0, if($B11=1, C$6, IF(and($B11>C$7,$B11<=sum(C$8,C$7)),(C$5-C$6)/(C$8-1),"")),IF($B11=1,C$6,IF(and($B11>C$7,$B11<=sum(C$8,C$7)),(C$5-C$6)/C$8,""))) -> 4500000 | D11: =if(D$7=0, if($B11=1, D$6, IF(and($B11>D$7,$B11<=sum(D$8,D$7)),(D$5-D$6)/(D$8-1),"")),IF($B11=1,D$6,IF(and($B11>D$7,$B11<=sum(D$8,D$7)),(D$5-D$6)/D$8,""))) | E11: =if(E$7=0, if($B11=1, E$6, IF(and($B11>E$7,$B11<=sum(E$8,E$7)),(E$5-E$6)/(E$8-1),"")),IF($B11=1,E$6,IF(and($B11>E$7,$B11<=sum(E$8,E$7)),(E$5-E$6)/E$8,""))) | F11: =if(F$7=0, if($B11=1, F$6, IF(and($B11>F$7,$B11<=sum(F$8,F$7)),(F$5-F$6)/(F$8-1),"")),IF($B11=1,F$6,IF(and($B11>F$7,$B11<=sum(F$8,F$7)),(F$5-F$6)/F$8,""))) | G11: =if(G$7=0, if($B11=1, G$6, IF(and($B11>G$7,$B11<=sum(G$8,G$7)),(G$5-G$6)/(G$8-1),"")),IF($B11=1,G$6,IF(and($B11>G$7,$B11<=sum(G$8,G$7)),(G$5-G$6)/G$8,""))) | H11: =if(H$7=0, if($B11=1, H$6, IF(and($B11>H$7,$B11<=sum(H$8,H$7)),(H$5-H$6)/(H$8-1),"")),IF($B11=1,H$6,IF(and($B11>H$7,$B11<=sum(H$8,H$7)),(H$5-H$6)/H$8,""))) | I11: =if(I$7=0, if($B11=1, I$6, IF(and($B11>I$7,$B11<=sum(I$8,I$7)),(I$5-I$6)/(I$8-1),"")),IF($B11=1,I$6,IF(and($B11>I$7,$B11<=sum(I$8,I$7)),(I$5-I$6)/I$8,""))) -> 2914285.7 | J11: =if(J$7=0, if($B11=1, J$6, IF(and($B11>J$7,$B11<=sum(J$8,J$7)),(J$5-J$6)/(J$8-1),"")),IF($B11=1,J$6,IF(and($B11>J$7,$B11<=sum(J$8,J$7)),(J$5-J$6)/J$8,""))) -> 2881355.9 | ... N11: =if(N$7=0, if($B11=1, N$6, IF(and($B11>N$7,$B11<=sum(N$8,N$7)),(N$5-N$6)/(N$8-1),"")),IF($B11=1,N$6,IF(and($B11>N$7,$B11<=sum(N$8,N$7)),(N$5-N$6)/N$8,""))) -> 1142857.1 | O11: =SUM(C11:N11) -> 13256681 | P11: =N11+SUM(E11:H11) -> 1142857.1 | Q11: =Q10+SUM(C11:N11) -> 1.9451336e+08 | R11: =Q11/$O$5 -> 0.19451336 | S11: =R11-R10 -> 0.013256681 | T11: =(R11/R10)-100% -> 0.073137611 | U11: =$Q11*U$3 -> 6418940.9 | V11: =$Q11*V$3 -> 9725668.1 | W11: =$Q11*W$3 -> 29177004 | X11: =$Q11*X$3 -> 48628340 | Y11: =$Q11*Y$3 -> 97256681 | Z11: =$Q11*Z$3 -> 1.9451336e+08 | AA11: =$Q11*AA$3 -> 320947046 | AB11: =$Q11*AB$3 -> 486283403 | AC11: =$Q11*AC$3 -> 9.7256681e+08
B12: 4 | C12: =if(C$7=0, if($B12=1, C$6, IF(and($B12>C$7,$B12<=sum(C$8,C$7)),(C$5-C$6)/(C$8-1),"")),IF($B12=1,C$6,IF(and($B12>C$7,$B12<=sum(C$8,C$7)),(C$5-C$6)/C$8,""))) -> 4500000 | D12: =if(D$7=0, if($B12=1, D$6, IF(and($B12>D$7,$B12<=sum(D$8,D$7)),(D$5-D$6)/(D$8-1),"")),IF($B12=1,D$6,IF(and($B12>D$7,$B12<=sum(D$8,D$7)),(D$5-D$6)/D$8,""))) | E12: =if(E$7=0, if($B12=1, E$6, IF(and($B12>E$7,$B12<=sum(E$8,E$7)),(E$5-E$6)/(E$8-1),"")),IF($B12=1,E$6,IF(and($B12>E$7,$B12<=sum(E$8,E$7)),(E$5-E$6)/E$8,""))) | F12: =if(F$7=0, if($B12=1, F$6, IF(and($B12>F$7,$B12<=sum(F$8,F$7)),(F$5-F$6)/(F$8-1),"")),IF($B12=1,F$6,IF(and($B12>F$7,$B12<=sum(F$8,F$7)),(F$5-F$6)/F$8,""))) | G12: =if(G$7=0, if($B12=1, G$6, IF(and($B12>G$7,$B12<=sum(G$8,G$7)),(G$5-G$6)/(G$8-1),"")),IF($B12=1,G$6,IF(and($B12>G$7,$B12<=sum(G$8,G$7)),(G$5-G$6)/G$8,""))) | H12: =if(H$7=0, if($B12=1, H$6, IF(and($B12>H$7,$B12<=sum(H$8,H$7)),(H$5-H$6)/(H$8-1),"")),IF($B12=1,H$6,IF(and($B12>H$7,$B12<=sum(H$8,H$7)),(H$5-H$6)/H$8,""))) | I12: =if(I$7=0, if($B12=1, I$6, IF(and($B12>I$7,$B12<=sum(I$8,I$7)),(I$5-I$6)/(I$8-1),"")),IF($B12=1,I$6,IF(and($B12>I$7,$B12<=sum(I$8,I$7)),(I$5-I$6)/I$8,""))) -> 2914285.7 | J12: =if(J$7=0, if($B12=1, J$6, IF(and($B12>J$7,$B12<=sum(J$8,J$7)),(J$5-J$6)/(J$8-1),"")),IF($B12=1,J$6,IF(and($B12>J$7,$B12<=sum(J$8,J$7)),(J$5-J$6)/J$8,""))) -> 2881355.9 | ... N12: =if(N$7=0, if($B12=1, N$6, IF(and($B12>N$7,$B12<=sum(N$8,N$7)),(N$5-N$6)/(N$8-1),"")),IF($B12=1,N$6,IF(and($B12>N$7,$B12<=sum(N$8,N$7)),(N$5-N$6)/N$8,""))) -> 1142857.1 | O12: =SUM(C12:N12) -> 13256681 | P12: =N12+SUM(E12:H12) -> 1142857.1 | Q12: =Q11+SUM(C12:N12) -> 2.0777004e+08 | R12: =Q12/$O$5 -> 0.20777004 | S12: =R12-R11 -> 0.013256681 | T12: =(R12/R11)-100% -> 0.068153059 | U12: =$Q12*U$3 -> 6856411.4 | V12: =$Q12*V$3 -> 10388502 | W12: =$Q12*W$3 -> 31165506 | X12: =$Q12*X$3 -> 51942510 | Y12: =$Q12*Y$3 -> 1.0388502e+08 | Z12: =$Q12*Z$3 -> 2.0777004e+08 | AA12: =$Q12*AA$3 -> 342820569 | AB12: =$Q12*AB$3 -> 5.194251e+08 | AC12: =$Q12*AC$3 -> 1038850209
B13: 5 | C13: =if(C$7=0, if($B13=1, C$6, IF(and($B13>C$7,$B13<=sum(C$8,C$7)),(C$5-C$6)/(C$8-1),"")),IF($B13=1,C$6,IF(and($B13>C$7,$B13<=sum(C$8,C$7)),(C$5-C$6)/C$8,""))) -> 4500000 | D13: =if(D$7=0, if($B13=1, D$6, IF(and($B13>D$7,$B13<=sum(D$8,D$7)),(D$5-D$6)/(D$8-1),"")),IF($B13=1,D$6,IF(and($B13>D$7,$B13<=sum(D$8,D$7)),(D$5-D$6)/D$8,""))) | E13: =if(E$7=0, if($B13=1, E$6, IF(and($B13>E$7,$B13<=sum(E$8,E$7)),(E$5-E$6)/(E$8-1),"")),IF($B13=1,E$6,IF(and($B13>E$7,$B13<=sum(E$8,E$7)),(E$5-E$6)/E$8,""))) | F13: =if(F$7=0, if($B13=1, F$6, IF(and($B13>F$7,$B13<=sum(F$8,F$7)),(F$5-F$6)/(F$8-1),"")),IF($B13=1,F$6,IF(and($B13>F$7,$B13<=sum(F$8,F$7)),(F$5-F$6)/F$8,""))) | G13: =if(G$7=0, if($B13=1, G$6, IF(and($B13>G$7,$B13<=sum(G$8,G$7)),(G$5-G$6)/(G$8-1),"")),IF($B13=1,G$6,IF(and($B13>G$7,$B13<=sum(G$8,G$7)),(G$5-G$6)/G$8,""))) | H13: =if(H$7=0, if($B13=1, H$6, IF(and($B13>H$7,$B13<=sum(H$8,H$7)),(H$5-H$6)/(H$8-1),"")),IF($B13=1,H$6,IF(and($B13>H$7,$B13<=sum(H$8,H$7)),(H$5-H$6)/H$8,""))) | I13: =if(I$7=0, if($B13=1, I$6, IF(and($B13>I$7,$B13<=sum(I$8,I$7)),(I$5-I$6)/(I$8-1),"")),IF($B13=1,I$6,IF(and($B13>I$7,$B13<=sum(I$8,I$7)),(I$5-I$6)/I$8,""))) -> 2914285.7 | J13: =if(J$7=0, if($B13=1, J$6, IF(and($B13>J$7,$B13<=sum(J$8,J$7)),(J$5-J$6)/(J$8-1),"")),IF($B13=1,J$6,IF(and($B13>J$7,$B13<=sum(J$8,J$7)),(J$5-J$6)/J$8,""))) -> 2881355.9 | ... N13: =if(N$7=0, if($B13=1, N$6, IF(and($B13>N$7,$B13<=sum(N$8,N$7)),(N$5-N$6)/(N$8-1),"")),IF($B13=1,N$6,IF(and($B13>N$7,$B13<=sum(N$8,N$7)),(N$5-N$6)/N$8,""))) -> 1142857.1 | O13: =SUM(C13:N13) -> 13256681 | P13: =N13+SUM(E13:H13) -> 1142857.1 | Q13: =Q12+SUM(C13:N13) -> 2.2102672e+08 | R13: =Q13/$O$5 -> 0.22102672 | S13: =R13-R12 -> 0.013256681 | T13: =(R13/R12)-100% -> 0.063804582 | U13: =$Q13*U$3 -> 7293881.8 | V13: =$Q13*V$3 -> 11051336 | W13: =$Q13*W$3 -> 33154008 | X13: =$Q13*X$3 -> 55256681 | Y13: =$Q13*Y$3 -> 1.1051336e+08 | Z13: =$Q13*Z$3 -> 2.2102672e+08 | AA13: =$Q13*AA$3 -> 364694092 | AB13: =$Q13*AB$3 -> 5.5256681e+08 | AC13: =$Q13*AC$3 -> 1105133612
B14: 6 | C14: =if(C$7=0, if($B14=1, C$6, IF(and($B14>C$7,$B14<=sum(C$8,C$7)),(C$5-C$6)/(C$8-1),"")),IF($B14=1,C$6,IF(and($B14>C$7,$B14<=sum(C$8,C$7)),(C$5-C$6)/C$8,""))) -> 4500000 | D14: =if(D$7=0, if($B14=1, D$6, IF(and($B14>D$7,$B14<=sum(D$8,D$7)),(D$5-D$6)/(D$8-1),"")),IF($B14=1,D$6,IF(and($B14>D$7,$B14<=sum(D$8,D$7)),(D$5-D$6)/D$8,""))) | E14: =if(E$7=0, if($B14=1, E$6, IF(and($B14>E$7,$B14<=sum(E$8,E$7)),(E$5-E$6)/(E$8-1),"")),IF($B14=1,E$6,IF(and($B14>E$7,$B14<=sum(E$8,E$7)),(E$5-E$6)/E$8,""))) | F14: =if(F$7=0, if($B14=1, F$6, IF(and($B14>F$7,$B14<=sum(F$8,F$7)),(F$5-F$6)/(F$8-1),"")),IF($B14=1,F$6,IF(and($B14>F$7,$B14<=sum(F$8,F$7)),(F$5-F$6)/F$8,""))) | G14: =if(G$7=0, if($B14=1, G$6, IF(and($B14>G$7,$B14<=sum(G$8,G$7)),(G$5-G$6)/(G$8-1),"")),IF($B14=1,G$6,IF(and($B14>G$7,$B14<=sum(G$8,G$7)),(G$5-G$6)/G$8,""))) | H14: =if(H$7=0, if($B14=1, H$6, IF(and($B14>H$7,$B14<=sum(H$8,H$7)),(H$5-H$6)/(H$8-1),"")),IF($B14=1,H$6,IF(and($B14>H$7,$B14<=sum(H$8,H$7)),(H$5-H$6)/H$8,""))) | I14: =if(I$7=0, if($B14=1, I$6, IF(and($B14>I$7,$B14<=sum(I$8,I$7)),(I$5-I$6)/(I$8-1),"")),IF($B14=1,I$6,IF(and($B14>I$7,$B14<=sum(I$8,I$7)),(I$5-I$6)/I$8,""))) -> 2914285.7 | J14: =if(J$7=0, if($B14=1, J$6, IF(and($B14>J$7,$B14<=sum(J$8,J$7)),(J$5-J$6)/(J$8-1),"")),IF($B14=1,J$6,IF(and($B14>J$7,$B14<=sum(J$8,J$7)),(J$5-J$6)/J$8,""))) -> 2881355.9 | ... N14: =if(N$7=0, if($B14=1, N$6, IF(and($B14>N$7,$B14<=sum(N$8,N$7)),(N$5-N$6)/(N$8-1),"")),IF($B14=1,N$6,IF(and($B14>N$7,$B14<=sum(N$8,N$7)),(N$5-N$6)/N$8,""))) -> 1142857.1 | O14: =SUM(C14:N14) -> 13256681 | P14: =N14+SUM(E14:H14) -> 1142857.1 | Q14: =Q13+SUM(C14:N14) -> 234283403 | R14: =Q14/$O$5 -> 0.2342834 | S14: =R14-R13 -> 0.013256681 | T14: =(R14/R13)-100% -> 0.059977728 | U14: =$Q14*U$3 -> 7731352.3 | V14: =$Q14*V$3 -> 11714170 | W14: =$Q14*W$3 -> 35142510 | X14: =$Q14*X$3 -> 58570851 | Y14: =$Q14*Y$3 -> 1.171417e+08 | Z14: =$Q14*Z$3 -> 234283403 | AA14: =$Q14*AA$3 -> 386567615 | AB14: =$Q14*AB$3 -> 5.8570851e+08 | AC14: =$Q14*AC$3 -> 1171417015
B15: 7 | C15: =if(C$7=0, if($B15=1, C$6, IF(and($B15>C$7,$B15<=sum(C$8,C$7)),(C$5-C$6)/(C$8-1),"")),IF($B15=1,C$6,IF(and($B15>C$7,$B15<=sum(C$8,C$7)),(C$5-C$6)/C$8,""))) -> 4500000 | D15: =if(D$7=0, if($B15=1, D$6, IF(and($B15>D$7,$B15<=sum(D$8,D$7)),(D$5-D$6)/(D$8-1),"")),IF($B15=1,D$6,IF(and($B15>D$7,$B15<=sum(D$8,D$7)),(D$5-D$6)/D$8,""))) | E15: =if(E$7=0, if($B15=1, E$6, IF(and($B15>E$7,$B15<=sum(E$8,E$7)),(E$5-E$6)/(E$8-1),"")),IF($B15=1,E$6,IF(and($B15>E$7,$B15<=sum(E$8,E$7)),(E$5-E$6)/E$8,""))) | F15: =if(F$7=0, if($B15=1, F$6, IF(and($B15>F$7,$B15<=sum(F$8,F$7)),(F$5-F$6)/(F$8-1),"")),IF($B15=1,F$6,IF(and($B15>F$7,$B15<=sum(F$8,F$7)),(F$5-F$6)/F$8,""))) | G15: =if(G$7=0, if($B15=1, G$6, IF(and($B15>G$7,$B15<=sum(G$8,G$7)),(G$5-G$6)/(G$8-1),"")),IF($B15=1,G$6,IF(and($B15>G$7,$B15<=sum(G$8,G$7)),(G$5-G$6)/G$8,""))) | H15: =if(H$7=0, if($B15=1, H$6, IF(and($B15>H$7,$B15<=sum(H$8,H$7)),(H$5-H$6)/(H$8-1),"")),IF($B15=1,H$6,IF(and($B15>H$7,$B15<=sum(H$8,H$7)),(H$5-H$6)/H$8,""))) -> 2222222.2 | I15: =if(I$7=0, if($B15=1, I$6, IF(and($B15>I$7,$B15<=sum(I$8,I$7)),(I$5-I$6)/(I$8-1),"")),IF($B15=1,I$6,IF(and($B15>I$7,$B15<=sum(I$8,I$7)),(I$5-I$6)/I$8,""))) -> 2914285.7 | J15: =if(J$7=0, if($B15=1, J$6, IF(and($B15>J$7,$B15<=sum(J$8,J$7)),(J$5-J$6)/(J$8-1),"")),IF($B15=1,J$6,IF(and($B15>J$7,$B15<=sum(J$8,J$7)),(J$5-J$6)/J$8,""))) -> 2881355.9 | ... N15: =if(N$7=0, if($B15=1, N$6, IF(and($B15>N$7,$B15<=sum(N$8,N$7)),(N$5-N$6)/(N$8-1),"")),IF($B15=1,N$6,IF(and($B15>N$7,$B15<=sum(N$8,N$7)),(N$5-N$6)/N$8,""))) -> 1142857.1 | O15: =SUM(C15:N15) -> 15478903 | P15: =N15+SUM(E15:H15) -> 3365079.4 | Q15: =Q14+SUM(C15:N15) -> 2.4976231e+08 | R15: =Q15/$O$5 -> 0.24976231 | S15: =R15-R14 -> 0.015478903 | T15: =(R15/R14)-100% -> 0.066069139 | U15: =$Q15*U$3 -> 8242156.1 | V15: =$Q15*V$3 -> 12488115 | W15: =$Q15*W$3 -> 37464346 | X15: =$Q15*X$3 -> 62440576 | Y15: =$Q15*Y$3 -> 1.2488115e+08 | Z15: =$Q15*Z$3 -> 2.4976231e+08 | AA15: =$Q15*AA$3 -> 4.121078e+08 | AB15: =$Q15*AB$3 -> 6.2440576e+08 | AC15: =$Q15*AC$3 -> 1248811529
B16: 8 | C16: =if(C$7=0, if($B16=1, C$6, IF(and($B16>C$7,$B16<=sum(C$8,C$7)),(C$5-C$6)/(C$8-1),"")),IF($B16=1,C$6,IF(and($B16>C$7,$B16<=sum(C$8,C$7)),(C$5-C$6)/C$8,""))) -> 4500000 | D16: =if(D$7=0, if($B16=1, D$6, IF(and($B16>D$7,$B16<=sum(D$8,D$7)),(D$5-D$6)/(D$8-1),"")),IF($B16=1,D$6,IF(and($B16>D$7,$B16<=sum(D$8,D$7)),(D$5-D$6)/D$8,""))) | E16: =if(E$7=0, if($B16=1, E$6, IF(and($B16>E$7,$B16<=sum(E$8,E$7)),(E$5-E$6)/(E$8-1),"")),IF($B16=1,E$6,IF(and($B16>E$7,$B16<=sum(E$8,E$7)),(E$5-E$6)/E$8,""))) | F16: =if(F$7=0, if($B16=1, F$6, IF(and($B16>F$7,$B16<=sum(F$8,F$7)),(F$5-F$6)/(F$8-1),"")),IF($B16=1,F$6,IF(and($B16>F$7,$B16<=sum(F$8,F$7)),(F$5-F$6)/F$8,""))) | G16: =if(G$7=0, if($B16=1, G$6, IF(and($B16>G$7,$B16<=sum(G$8,G$7)),(G$5-G$6)/(G$8-1),"")),IF($B16=1,G$6,IF(and($B16>G$7,$B16<=sum(G$8,G$7)),(G$5-G$6)/G$8,""))) | H16: =if(H$7=0, if($B16=1, H$6, IF(and($B16>H$7,$B16<=sum(H$8,H$7)),(H$5-H$6)/(H$8-1),"")),IF($B16=1,H$6,IF(and($B16>H$7,$B16<=sum(H$8,H$7)),(H$5-H$6)/H$8,""))) -> 2222222.2 | I16: =if(I$7=0, if($B16=1, I$6, IF(and($B16>I$7,$B16<=sum(I$8,I$7)),(I$5-I$6)/(I$8-1),"")),IF($B16=1,I$6,IF(and($B16>I$7,$B16<=sum(I$8,I$7)),(I$5-I$6)/I$8,""))) -> 2914285.7 | J16: =if(J$7=0, if($B16=1, J$6, IF(and($B16>J$7,$B16<=sum(J$8,J$7)),(J$5-J$6)/(J$8-1),"")),IF($B16=1,J$6,IF(and($B16>J$7,$B16<=sum(J$8,J$7)),(J$5-J$6)/J$8,""))) -> 2881355.9 | ... N16: =if(N$7=0, if($B16=1, N$6, IF(and($B16>N$7,$B16<=sum(N$8,N$7)),(N$5-N$6)/(N$8-1),"")),IF($B16=1,N$6,IF(and($B16>N$7,$B16<=sum(N$8,N$7)),(N$5-N$6)/N$8,""))) -> 1142857.1 | O16: =SUM(C16:N16) -> 15478903 | P16: =N16+SUM(E16:H16) -> 3365079.4 | Q16: =Q15+SUM(C16:N16) -> 2.6524121e+08 | R16: =Q16/$O$5 -> 0.26524121 | S16: =R16-R15 -> 0.015478903 | T16: =(R16/R15)-100% -> 0.061974535 | U16: =$Q16*U$3 -> 8752959.9 | V16: =$Q16*V$3 -> 13262060 | W16: =$Q16*W$3 -> 39786181 | X16: =$Q16*X$3 -> 66310302 | Y16: =$Q16*Y$3 -> 1.326206e+08 | Z16: =$Q16*Z$3 -> 2.6524121e+08 | AA16: =$Q16*AA$3 -> 4.3764799e+08 | AB16: =$Q16*AB$3 -> 6.6310302e+08 | AC16: =$Q16*AC$3 -> 1326206043
B17: 9 | C17: =if(C$7=0, if($B17=1, C$6, IF(and($B17>C$7,$B17<=sum(C$8,C$7)),(C$5-C$6)/(C$8-1),"")),IF($B17=1,C$6,IF(and($B17>C$7,$B17<=sum(C$8,C$7)),(C$5-C$6)/C$8,""))) -> 4500000 | D17: =if(D$7=0, if($B17=1, D$6, IF(and($B17>D$7,$B17<=sum(D$8,D$7)),(D$5-D$6)/(D$8-1),"")),IF($B17=1,D$6,IF(and($B17>D$7,$B17<=sum(D$8,D$7)),(D$5-D$6)/D$8,""))) | E17: =if(E$7=0, if($B17=1, E$6, IF(and($B17>E$7,$B17<=sum(E$8,E$7)),(E$5-E$6)/(E$8-1),"")),IF($B17=1,E$6,IF(and($B17>E$7,$B17<=sum(E$8,E$7)),(E$5-E$6)/E$8,""))) | F17: =if(F$7=0, if($B17=1, F$6, IF(and($B17>F$7,$B17<=sum(F$8,F$7)),(F$5-F$6)/(F$8-1),"")),IF($B17=1,F$6,IF(and($B17>F$7,$B17<=sum(F$8,F$7)),(F$5-F$6)/F$8,""))) | G17: =if(G$7=0, if($B17=1, G$6, IF(and($B17>G$7,$B17<=sum(G$8,G$7)),(G$5-G$6)/(G$8-1),"")),IF($B17=1,G$6,IF(and($B17>G$7,$B17<=sum(G$8,G$7)),(G$5-G$6)/G$8,""))) | H17: =if(H$7=0, if($B17=1, H$6, IF(and($B17>H$7,$B17<=sum(H$8,H$7)),(H$5-H$6)/(H$8-1),"")),IF($B17=1,H$6,IF(and($B17>H$7,$B17<=sum(H$8,H$7)),(H$5-H$6)/H$8,""))) -> 2222222.2 | I17: =if(I$7=0, if($B17=1, I$6, IF(and($B17>I$7,$B17<=sum(I$8,I$7)),(I$5-I$6)/(I$8-1),"")),IF($B17=1,I$6,IF(and($B17>I$7,$B17<=sum(I$8,I$7)),(I$5-I$6)/I$8,""))) -> 2914285.7 | J17: =if(J$7=0, if($B17=1, J$6, IF(and($B17>J$7,$B17<=sum(J$8,J$7)),(J$5-J$6)/(J$8-1),"")),IF($B17=1,J$6,IF(and($B17>J$7,$B17<=sum(J$8,J$7)),(J$5-J$6)/J$8,""))) -> 2881355.9 | ... N17: =if(N$7=0, if($B17=1, N$6, IF(and($B17>N$7,$B17<=sum(N$8,N$7)),(N$5-N$6)/(N$8-1),"")),IF($B17=1,N$6,IF(and($B17>N$7,$B17<=sum(N$8,N$7)),(N$5-N$6)/N$8,""))) -> 1142857.1 | O17: =SUM(C17:N17) -> 15478903 | P17: =N17+SUM(E17:H17) -> 3365079.4 | Q17: =Q16+SUM(C17:N17) -> 2.8072011e+08 | R17: =Q17/$O$5 -> 0.28072011 | S17: =R17-R16 -> 0.015478903 | T17: =(R17/R16)-100% -> 0.058357836 | U17: =$Q17*U$3 -> 9263763.7 | V17: =$Q17*V$3 -> 14036006 | W17: =$Q17*W$3 -> 42108017 | X17: =$Q17*X$3 -> 70180028 | Y17: =$Q17*Y$3 -> 1.4036006e+08 | Z17: =$Q17*Z$3 -> 2.8072011e+08 | AA17: =$Q17*AA$3 -> 463188184 | AB17: =$Q17*AB$3 -> 7.0180028e+08 | AC17: =$Q17*AC$3 -> 1403600558
B18: 10 | C18: =if(C$7=0, if($B18=1, C$6, IF(and($B18>C$7,$B18<=sum(C$8,C$7)),(C$5-C$6)/(C$8-1),"")),IF($B18=1,C$6,IF(and($B18>C$7,$B18<=sum(C$8,C$7)),(C$5-C$6)/C$8,""))) -> 4500000 | D18: =if(D$7=0, if($B18=1, D$6, IF(and($B18>D$7,$B18<=sum(D$8,D$7)),(D$5-D$6)/(D$8-1),"")),IF($B18=1,D$6,IF(and($B18>D$7,$B18<=sum(D$8,D$7)),(D$5-D$6)/D$8,""))) | E18: =if(E$7=0, if($B18=1, E$6, IF(and($B18>E$7,$B18<=sum(E$8,E$7)),(E$5-E$6)/(E$8-1),"")),IF($B18=1,E$6,IF(and($B18>E$7,$B18<=sum(E$8,E$7)),(E$5-E$6)/E$8,""))) | F18: =if(F$7=0, if($B18=1, F$6, IF(and($B18>F$7,$B18<=sum(F$8,F$7)),(F$5-F$6)/(F$8-1),"")),IF($B18=1,F$6,IF(and($B18>F$7,$B18<=sum(F$8,F$7)),(F$5-F$6)/F$8,""))) | G18: =if(G$7=0, if($B18=1, G$6, IF(and($B18>G$7,$B18<=sum(G$8,G$7)),(G$5-G$6)/(G$8-1),"")),IF($B18=1,G$6,IF(and($B18>G$7,$B18<=sum(G$8,G$7)),(G$5-G$6)/G$8,""))) | H18: =if(H$7=0, if($B18=1, H$6, IF(and($B18>H$7,$B18<=sum(H$8,H$7)),(H$5-H$6)/(H$8-1),"")),IF($B18=1,H$6,IF(and($B18>H$7,$B18<=sum(H$8,H$7)),(H$5-H$6)/H$8,""))) -> 2222222.2 | I18: =if(I$7=0, if($B18=1, I$6, IF(and($B18>I$7,$B18<=sum(I$8,I$7)),(I$5-I$6)/(I$8-1),"")),IF($B18=1,I$6,IF(and($B18>I$7,$B18<=sum(I$8,I$7)),(I$5-I$6)/I$8,""))) -> 2914285.7 | J18: =if(J$7=0, if($B18=1, J$6, IF(and($B18>J$7,$B18<=sum(J$8,J$7)),(J$5-J$6)/(J$8-1),"")),IF($B18=1,J$6,IF(and($B18>J$7,$B18<=sum(J$8,J$7)),(J$5-J$6)/J$8,""))) -> 2881355.9 | ... N18: =if(N$7=0, if($B18=1, N$6, IF(and($B18>N$7,$B18<=sum(N$8,N$7)),(N$5-N$6)/(N$8-1),"")),IF($B18=1,N$6,IF(and($B18>N$7,$B18<=sum(N$8,N$7)),(N$5-N$6)/N$8,""))) -> 1142857.1 | O18: =SUM(C18:N18) -> 15478903 | P18: =N18+SUM(E18:H18) -> 3365079.4 | Q18: =Q17+SUM(C18:N18) -> 2.9619901e+08 | R18: =Q18/$O$5 -> 0.29619901 | S18: =R18-R17 -> 0.015478903 | T18: =(R18/R17)-100% -> 0.055139985 | U18: =$Q18*U$3 -> 9774567.5 | V18: =$Q18*V$3 -> 14809951 | W18: =$Q18*W$3 -> 44429852 | X18: =$Q18*X$3 -> 74049754 | Y18: =$Q18*Y$3 -> 1.4809951e+08 | Z18: =$Q18*Z$3 -> 2.9619901e+08 | AA18: =$Q18*AA$3 -> 4.8872837e+08 | AB18: =$Q18*AB$3 -> 7.4049754e+08 | AC18: =$Q18*AC$3 -> 1480995072
B19: 11 | C19: =if(C$7=0, if($B19=1, C$6, IF(and($B19>C$7,$B19<=sum(C$8,C$7)),(C$5-C$6)/(C$8-1),"")),IF($B19=1,C$6,IF(and($B19>C$7,$B19<=sum(C$8,C$7)),(C$5-C$6)/C$8,""))) -> 4500000 | D19: =if(D$7=0, if($B19=1, D$6, IF(and($B19>D$7,$B19<=sum(D$8,D$7)),(D$5-D$6)/(D$8-1),"")),IF($B19=1,D$6,IF(and($B19>D$7,$B19<=sum(D$8,D$7)),(D$5-D$6)/D$8,""))) | E19: =if(E$7=0, if($B19=1, E$6, IF(and($B19>E$7,$B19<=sum(E$8,E$7)),(E$5-E$6)/(E$8-1),"")),IF($B19=1,E$6,IF(and($B19>E$7,$B19<=sum(E$8,E$7)),(E$5-E$6)/E$8,""))) | F19: =if(F$7=0, if($B19=1, F$6, IF(and($B19>F$7,$B19<=sum(F$8,F$7)),(F$5-F$6)/(F$8-1),"")),IF($B19=1,F$6,IF(and($B19>F$7,$B19<=sum(F$8,F$7)),(F$5-F$6)/F$8,""))) | G19: =if(G$7=0, if($B19=1, G$6, IF(and($B19>G$7,$B19<=sum(G$8,G$7)),(G$5-G$6)/(G$8-1),"")),IF($B19=1,G$6,IF(and($B19>G$7,$B19<=sum(G$8,G$7)),(G$5-G$6)/G$8,""))) | H19: =if(H$7=0, if($B19=1, H$6, IF(and($B19>H$7,$B19<=sum(H$8,H$7)),(H$5-H$6)/(H$8-1),"")),IF($B19=1,H$6,IF(and($B19>H$7,$B19<=sum(H$8,H$7)),(H$5-H$6)/H$8,""))) -> 2222222.2 | I19: =if(I$7=0, if($B19=1, I$6, IF(and($B19>I$7,$B19<=sum(I$8,I$7)),(I$5-I$6)/(I$8-1),"")),IF($B19=1,I$6,IF(and($B19>I$7,$B19<=sum(I$8,I$7)),(I$5-I$6)/I$8,""))) -> 2914285.7 | J19: =if(J$7=0, if($B19=1, J$6, IF(and($B19>J$7,$B19<=sum(J$8,J$7)),(J$5-J$6)/(J$8-1),"")),IF($B19=1,J$6,IF(and($B19>J$7,$B19<=sum(J$8,J$7)),(J$5-J$6)/J$8,""))) -> 2881355.9 | ... N19: =if(N$7=0, if($B19=1, N$6, IF(and($B19>N$7,$B19<=sum(N$8,N$7)),(N$5-N$6)/(N$8-1),"")),IF($B19=1,N$6,IF(and($B19>N$7,$B19<=sum(N$8,N$7)),(N$5-N$6)/N$8,""))) -> 1142857.1 | O19: =SUM(C19:N19) -> 15478903 | P19: =N19+SUM(E19:H19) -> 3365079.4 | Q19: =Q18+SUM(C19:N19) -> 3.1167792e+08 | R19: =Q19/$O$5 -> 0.31167792 | S19: =R19-R18 -> 0.015478903 | T19: =(R19/R18)-100% -> 0.052258455 | U19: =$Q19*U$3 -> 10285371 | V19: =$Q19*V$3 -> 15583896 | W19: =$Q19*W$3 -> 46751688 | X19: =$Q19*X$3 -> 77919479 | Y19: =$Q19*Y$3 -> 1.5583896e+08 | Z19: =$Q19*Z$3 -> 3.1167792e+08 | AA19: =$Q19*AA$3 -> 5.1426856e+08 | AB19: =$Q19*AB$3 -> 779194793 | AC19: =$Q19*AC$3 -> 1558389586
B20: 12 | C20: =if(C$7=0, if($B20=1, C$6, IF(and($B20>C$7,$B20<=sum(C$8,C$7)),(C$5-C$6)/(C$8-1),"")),IF($B20=1,C$6,IF(and($B20>C$7,$B20<=sum(C$8,C$7)),(C$5-C$6)/C$8,""))) -> 4500000 | D20: =if(D$7=0, if($B20=1, D$6, IF(and($B20>D$7,$B20<=sum(D$8,D$7)),(D$5-D$6)/(D$8-1),"")),IF($B20=1,D$6,IF(and($B20>D$7,$B20<=sum(D$8,D$7)),(D$5-D$6)/D$8,""))) | E20: =if(E$7=0, if($B20=1, E$6, IF(and($B20>E$7,$B20<=sum(E$8,E$7)),(E$5-E$6)/(E$8-1),"")),IF($B20=1,E$6,IF(and($B20>E$7,$B20<=sum(E$8,E$7)),(E$5-E$6)/E$8,""))) | F20: =if(F$7=0, if($B20=1, F$6, IF(and($B20>F$7,$B20<=sum(F$8,F$7)),(F$5-F$6)/(F$8-1),"")),IF($B20=1,F$6,IF(and($B20>F$7,$B20<=sum(F$8,F$7)),(F$5-F$6)/F$8,""))) | G20: =if(G$7=0, if($B20=1, G$6, IF(and($B20>G$7,$B20<=sum(G$8,G$7)),(G$5-G$6)/(G$8-1),"")),IF($B20=1,G$6,IF(and($B20>G$7,$B20<=sum(G$8,G$7)),(G$5-G$6)/G$8,""))) | H20: =if(H$7=0, if($B20=1, H$6, IF(and($B20>H$7,$B20<=sum(H$8,H$7)),(H$5-H$6)/(H$8-1),"")),IF($B20=1,H$6,IF(and($B20>H$7,$B20<=sum(H$8,H$7)),(H$5-H$6)/H$8,""))) -> 2222222.2 | I20: =if(I$7=0, if($B20=1, I$6, IF(and($B20>I$7,$B20<=sum(I$8,I$7)),(I$5-I$6)/(I$8-1),"")),IF($B20=1,I$6,IF(and($B20>I$7,$B20<=sum(I$8,I$7)),(I$5-I$6)/I$8,""))) -> 2914285.7 | J20: =if(J$7=0, if($B20=1, J$6, IF(and($B20>J$7,$B20<=sum(J$8,J$7)),(J$5-J$6)/(J$8-1),"")),IF($B20=1,J$6,IF(and($B20>J$7,$B20<=sum(J$8,J$7)),(J$5-J$6)/J$8,""))) -> 2881355.9 | ... N20: =if(N$7=0, if($B20=1, N$6, IF(and($B20>N$7,$B20<=sum(N$8,N$7)),(N$5-N$6)/(N$8-1),"")),IF($B20=1,N$6,IF(and($B20>N$7,$B20<=sum(N$8,N$7)),(N$5-N$6)/N$8,""))) -> 1142857.1 | O20: =SUM(C20:N20) -> 15478903 | P20: =N20+SUM(E20:H20) -> 3365079.4 | Q20: =Q19+SUM(C20:N20) -> 327156820 | R20: =Q20/$O$5 -> 0.32715682 | S20: =R20-R19 -> 0.015478903 | T20: =(R20/R19)-100% -> 0.049663136 | U20: =$Q20*U$3 -> 10796175 | V20: =$Q20*V$3 -> 16357841 | W20: =$Q20*W$3 -> 49073523 | X20: =$Q20*X$3 -> 81789205 | Y20: =$Q20*Y$3 -> 163578410 | Z20: =$Q20*Z$3 -> 327156820 | AA20: =$Q20*AA$3 -> 539808753 | AB20: =$Q20*AB$3 -> 817892050 | AC20: =$Q20*AC$3 -> 1635784100
B21: 13 | C21: =if(C$7=0, if($B21=1, C$6, IF(and($B21>C$7,$B21<=sum(C$8,C$7)),(C$5-C$6)/(C$8-1),"")),IF($B21=1,C$6,IF(and($B21>C$7,$B21<=sum(C$8,C$7)),(C$5-C$6)/C$8,""))) -> 4500000 | D21: =if(D$7=0, if($B21=1, D$6, IF(and($B21>D$7,$B21<=sum(D$8,D$7)),(D$5-D$6)/(D$8-1),"")),IF($B21=1,D$6,IF(and($B21>D$7,$B21<=sum(D$8,D$7)),(D$5-D$6)/D$8,""))) | E21: =if(E$7=0, if($B21=1, E$6, IF(and($B21>E$7,$B21<=sum(E$8,E$7)),(E$5-E$6)/(E$8-1),"")),IF($B21=1,E$6,IF(and($B21>E$7,$B21<=sum(E$8,E$7)),(E$5-E$6)/E$8,""))) | F21: =if(F$7=0, if($B21=1, F$6, IF(and($B21>F$7,$B21<=sum(F$8,F$7)),(F$5-F$6)/(F$8-1),"")),IF($B21=1,F$6,IF(and($B21>F$7,$B21<=sum(F$8,F$7)),(F$5-F$6)/F$8,""))) -> 4722222.2 | G21: =if(G$7=0, if($B21=1, G$6, IF(and($B21>G$7,$B21<=sum(G$8,G$7)),(G$5-G$6)/(G$8-1),"")),IF($B21=1,G$6,IF(and($B21>G$7,$B21<=sum(G$8,G$7)),(G$5-G$6)/G$8,""))) -> 1111111.1 | H21: =if(H$7=0, if($B21=1, H$6, IF(and($B21>H$7,$B21<=sum(H$8,H$7)),(H$5-H$6)/(H$8-1),"")),IF($B21=1,H$6,IF(and($B21>H$7,$B21<=sum(H$8,H$7)),(H$5-H$6)/H$8,""))) -> 2222222.2 | I21: =if(I$7=0, if($B21=1, I$6, IF(and($B21>I$7,$B21<=sum(I$8,I$7)),(I$5-I$6)/(I$8-1),"")),IF($B21=1,I$6,IF(and($B21>I$7,$B21<=sum(I$8,I$7)),(I$5-I$6)/I$8,""))) -> 2914285.7 | J21: =if(J$7=0, if($B21=1, J$6, IF(and($B21>J$7,$B21<=sum(J$8,J$7)),(J$5-J$6)/(J$8-1),"")),IF($B21=1,J$6,IF(and($B21>J$7,$B21<=sum(J$8,J$7)),(J$5-J$6)/J$8,""))) -> 2881355.9 | ... N21: =if(N$7=0, if($B21=1, N$6, IF(and($B21>N$7,$B21<=sum(N$8,N$7)),(N$5-N$6)/(N$8-1),"")),IF($B21=1,N$6,IF(and($B21>N$7,$B21<=sum(N$8,N$7)),(N$5-N$6)/N$8,""))) -> 1142857.1 | O21: =SUM(C21:N21) -> 21994054 | P21: =N21+SUM(E21:H21) -> 9198412.7 | Q21: =Q20+SUM(C21:N21) -> 3.4915087e+08 | R21: =Q21/$O$5 -> 0.34915087 | S21: =R21-R20 -> 0.021994054 | T21: =(R21/R20)-100% -> 0.067227864 | U21: =$Q21*U$3 -> 11521979 | V21: =$Q21*V$3 -> 17457544 | W21: =$Q21*W$3 -> 52372631 | X21: =$Q21*X$3 -> 87287719 | Y21: =$Q21*Y$3 -> 1.7457544e+08 | Z21: =$Q21*Z$3 -> 3.4915087e+08 | AA21: =$Q21*AA$3 -> 5.7609894e+08 | AB21: =$Q21*AB$3 -> 8.7287719e+08 | AC21: =$Q21*AC$3 -> 1745754372
... B68: 60 | C68: =if(C$7=0, if($B68=1, C$6, IF(and($B68>C$7,$B68<=sum(C$8,C$7)),(C$5-C$6)/(C$8-1),"")),IF($B68=1,C$6,IF(and($B68>C$7,$B68<=sum(C$8,C$7)),(C$5-C$6)/C$8,""))) | D68: =if(D$7=0, if($B68=1, D$6, IF(and($B68>D$7,$B68<=sum(D$8,D$7)),(D$5-D$6)/(D$8-1),"")),IF($B68=1,D$6,IF(and($B68>D$7,$B68<=sum(D$8,D$7)),(D$5-D$6)/D$8,""))) | E68: =if(E$7=0, if($B68=1, E$6, IF(and($B68>E$7,$B68<=sum(E$8,E$7)),(E$5-E$6)/(E$8-1),"")),IF($B68=1,E$6,IF(and($B68>E$7,$B68<=sum(E$8,E$7)),(E$5-E$6)/E$8,""))) | F68: =if(F$7=0, if($B68=1, F$6, IF(and($B68>F$7,$B68<=sum(F$8,F$7)),(F$5-F$6)/(F$8-1),"")),IF($B68=1,F$6,IF(and($B68>F$7,$B68<=sum(F$8,F$7)),(F$5-F$6)/F$8,""))) | G68: =if(G$7=0, if($B68=1, G$6, IF(and($B68>G$7,$B68<=sum(G$8,G$7)),(G$5-G$6)/(G$8-1),"")),IF($B68=1,G$6,IF(and($B68>G$7,$B68<=sum(G$8,G$7)),(G$5-G$6)/G$8,""))) | H68: =if(H$7=0, if($B68=1, H$6, IF(and($B68>H$7,$B68<=sum(H$8,H$7)),(H$5-H$6)/(H$8-1),"")),IF($B68=1,H$6,IF(and($B68>H$7,$B68<=sum(H$8,H$7)),(H$5-H$6)/H$8,""))) | I68: =if(I$7=0, if($B68=1, I$6, IF(and($B68>I$7,$B68<=sum(I$8,I$7)),(I$5-I$6)/(I$8-1),"")),IF($B68=1,I$6,IF(and($B68>I$7,$B68<=sum(I$8,I$7)),(I$5-I$6)/I$8,""))) | J68: =if(J$7=0, if($B68=1, J$6, IF(and($B68>J$7,$B68<=sum(J$8,J$7)),(J$5-J$6)/(J$8-1),"")),IF($B68=1,J$6,IF(and($B68>J$7,$B68<=sum(J$8,J$7)),(J$5-J$6)/J$8,""))) -> 2881355.9 | ... N68: =if(N$7=0, if($B68=1, N$6, IF(and($B68>N$7,$B68<=sum(N$8,N$7)),(N$5-N$6)/(N$8-1),"")),IF($B68=1,N$6,IF(and($B68>N$7,$B68<=sum(N$8,N$7)),(N$5-N$6)/N$8,""))) | O68: =SUM(C68:N68) -> 5381355.9 | P68: =N68+SUM(E68:H68) -> 0 | Q68: =Q67+SUM(C68:N68) -> 1000000000 | R68: =Q68/$O$5 -> 1 | S68: =R68-R67 -> 0.0053813559 | T68: =(R68/R67)-100% -> 0.0054104716 | U68: =$Q68*U$3 -> 33000000 | V68: =$Q68*V$3 -> 50000000 | W68: =$Q68*W$3 -> 150000000 | X68: =$Q68*X$3 -> 250000000 | Y68: =$Q68*Y$3 -> 500000000 | Z68: =$Q68*Z$3 -> 1000000000 | AA68: =$Q68*AA$3 -> 1650000000 | AB68: =$Q68*AB$3 -> 2500000000 | AC68: =$Q68*AC$3 -> 5000000000
C69: =SUM(C9:C68) -> 100000000 | D69: =SUM(D9:D68) -> 20000000 | E69: =SUM(E9:E68) -> 0 | F69: =SUM(F9:F68) -> 170000000 | G69: =SUM(G9:G68) -> 40000000 | H69: =SUM(H9:H68) -> 80000000 | I69: =SUM(I9:I68) -> 120000000 | J69: =SUM(J9:J68) -> 200000000 | ... N69: =SUM(N9:N68) -> 40000000 | O69: =SUM(C69:N69) -> 1000000000 | P69: =SUM(E69:H69) -> 290000000

Sheet Nodes
B6: NODE DISTRIBUTION
B9: Total Nodes | D9: Total Supply | F9: Supply for Rewards
B10: 50000 | D10: 10000000 | F10: 0.2
B12: TIER | C12: ETH PRICE | D12: USD PRICE | E12: NODE QUANTITY | F12: CUMULATIVE NODES | G12: IMPLIED FDV (USD) | H12: NODE SALE AMOUNT (USD)
B13: 1 | C13: =ROUND(NodeSale!$C$7*(1+NodeSale!$C$12)^(B13-1),2) -> 0.15 | D13: =ROUND(C13*NodeSale!$C$10,0) -> 525 | E13: =ROUNDUP(NodeSale!$C$9*(1-NodeSale!$C$13)^(B13-1),0) -> 4000 | F13: =E13 -> 4000 | G13: =ROUNDUP(D13*F13*(NodeSale!$C$4/NodeSale!$C$3)/NodeSale!$C$9,0) -> 10500000 | H13: =D13*E13 -> 2100000
B14: =B13+1 -> 2 | C14: =ROUND(NodeSale!$C$7*(1+NodeSale!$C$12)^(B14-1),2) -> 0.16 | D14: =ROUND(C14*NodeSale!$C$10,0) -> 560 | E14: =ROUNDUP(NodeSale!$C$9*(1-NodeSale!$C$13)^(B14-1),0) -> 3686 | F14: =F13+E14 -> 7686 | G14: =ROUNDUP(D14*F14*(NodeSale!$C$4/NodeSale!$C$3)/NodeSale!$C$9,0) -> 21520800 | H14: =D14*E14 -> 2064160
B15: =B14+1 -> 3 | C15: =ROUND(NodeSale!$C$7*(1+NodeSale!$C$12)^(B15-1),2) -> 0.17 | D15: =ROUND(C15*NodeSale!$C$10,0) -> 595 | E15: =ROUNDUP(NodeSale!$C$9*(1-NodeSale!$C$13)^(B15-1),0) -> 3396 | F15: =F14+E15 -> 11082 | G15: =ROUNDUP(D15*F15*(NodeSale!$C$4/NodeSale!$C$3)/NodeSale!$C$9,0) -> 32968950 | H15: =D15*E15 -> 2020620
B16: =B15+1 -> 4 | C16: =ROUND(NodeSale!$C$7*(1+NodeSale!$C$12)^(B16-1),2) -> 0.18 | D16: =ROUND(C16*NodeSale!$C$10,0) -> 630 | E16: =ROUNDUP(NodeSale!$C$9*(1-NodeSale!$C$13)^(B16-1),0) -> 3128 | F16: =F15+E16 -> 14210 | G16: =ROUNDUP(D16*F16*(NodeSale!$C$4/NodeSale!$C$3)/NodeSale!$C$9,0) -> 44761500 | H16: =D16*E16 -> 1970640
B17: =B16+1 -> 5 | C17: =ROUND(NodeSale!$C$7*(1+NodeSale!$C$12)^(B17-1),2) -> 0.2 | D17: =ROUND(C17*NodeSale!$C$10,0) -> 700 | E17: =ROUNDUP(NodeSale!$C$9*(1-NodeSale!$C$13)^(B17-1),0) -> 2882 | F17: =F16+E17 -> 17092 | G17: =ROUNDUP(D17*F17*(NodeSale!$C$4/NodeSale!$C$3)/NodeSale!$C$9,0) -> 59822000 | H17: =D17*E17 -> 2017400
B18: =B17+1 -> 6 | C18: =ROUND(NodeSale!$C$7*(1+NodeSale!$C$12)^(B18-1),2) -> 0.21 | D18: =ROUND(C18*NodeSale!$C$10,0) -> 735 | E18: =ROUNDUP(NodeSale!$C$9*(1-NodeSale!$C$13)^(B18-1),0) -> 2655 | F18: =F17+E18 -> 19747 | G18: =ROUNDUP(D18*F18*(NodeSale!$C$4/NodeSale!$C$3)/NodeSale!$C$9,0) -> 72570225 | H18: =D18*E18 -> 1951425
B19: =B18+1 -> 7 | C19: =ROUND(NodeSale!$C$7*(1+NodeSale!$C$12)^(B19-1),2) -> 0.22 | D19: =ROUND(C19*NodeSale!$C$10,0) -> 770 | E19: =ROUNDUP(NodeSale!$C$9*(1-NodeSale!$C$13)^(B19-1),0) -> 2446 | F19: =F18+E19 -> 22193 | G19: =ROUNDUP(D19*F19*(NodeSale!$C$4/NodeSale!$C$3)/NodeSale!$C$9,0) -> 85443050 | H19: =D19*E19 -> 1883420
B20: =B19+1 -> 8 | C20: =ROUND(NodeSale!$C$7*(1+NodeSale!$C$12)^(B20-1),2) -> 0.24 | D20: =ROUND(C20*NodeSale!$C$10,0) -> 840 | E20: =ROUNDUP(NodeSale!$C$9*(1-NodeSale!$C$13)^(B20-1),0) -> 2254 | F20: =F19+E20 -> 24447 | G20: =ROUNDUP(D20*F20*(NodeSale!$C$4/NodeSale!$C$3)/NodeSale!$C$9,0) -> 102677400 | H20: =D20*E20 -> 1893360
B21: =B20+1 -> 9 | C21: =ROUND(NodeSale!$C$7*(1+NodeSale!$C$12)^(B21-1),2) -> 0.26 | D21: =ROUND(C21*NodeSale!$C$10,0) -> 910 | E21: =ROUNDUP(NodeSale!$C$9*(1-NodeSale!$C$13)^(B21-1),0) -> 2076 | F21: =F20+E21 -> 26523 | G21: =ROUNDUP(D21*F21*(NodeSale!$C$4/NodeSale!$C$3)/NodeSale!$C$9,0) -> 120679650 | H21: =D21*E21 -> 1889160
B22: =B21+1 -> 10 | C22: =ROUND(NodeSale!$C$7*(1+NodeSale!$C$12)^(B22-1),2) -> 0.27 | D22: =ROUND(C22*NodeSale!$C$10,0) -> 945 | E22: =ROUNDUP(NodeSale!$C$9*(1-NodeSale!$C$13)^(B22-1),0) -> 1913 | F22: =F21+E22 -> 28436 | G22: =ROUNDUP(D22*F22*(NodeSale!$C$4/NodeSale!$C$3)/NodeSale!$C$9,0) -> 134360100 | H22: =D22*E22 -> 1807785
B23: =B22+1 -> 11 | C23: =ROUND(NodeSale!$C$7*(1+NodeSale!$C$12)^(B23-1),2) -> 0.29 | D23: =ROUND(C23*NodeSale!$C$10,0) -> 1015 | E23: =ROUNDUP(NodeSale!$C$9*(1-NodeSale!$C$13)^(B23-1),0) -> 1763 | F23: =F22+E23 -> 30199 | G23: =ROUNDUP(D23*F23*(NodeSale!$C$4/NodeSale!$C$3)/NodeSale!$C$9,0) -> 153259925 | H23: =D23*E23 -> 1789445
B24: =B23+1 -> 12 | C24: =ROUND(NodeSale!$C$7*(1+NodeSale!$C$12)^(B24-1),2) -> 0.31 | D24: =ROUND(C24*NodeSale!$C$10,0) -> 1085 | E24: =ROUNDUP(NodeSale!$C$9*(1-NodeSale!$C$13)^(B24-1),0) -> 1624 | F24: =F23+E24 -> 31823 | G24: =ROUNDUP(D24*F24*(NodeSale!$C$4/NodeSale!$C$3)/NodeSale!$C$9,0) -> 172639775 | H24: =D24*E24 -> 1762040
B25: =B24+1 -> 13 | C25: =ROUND(NodeSale!$C$7*(1+NodeSale!$C$12)^(B25-1),2) -> 0.34 | D25: =ROUND(C25*NodeSale!$C$10,0) -> 1190 | E25: =ROUNDUP(NodeSale!$C$9*(1-NodeSale!$C$13)^(B25-1),0) -> 1496 | F25: =F24+E25 -> 33319 | G25: =ROUNDUP(D25*F25*(NodeSale!$C$4/NodeSale!$C$3)/NodeSale!$C$9,0) -> 198248050 | H25: =D25*E25 -> 1780240
... B62: =B61+1 -> 50 | C62: =ROUND(NodeSale!$C$7*(1+NodeSale!$C$12)^(B62-1),2) -> 4 | D62: =ROUND(C62*NodeSale!$C$10,0) -> 14000 | E62: =ROUNDUP(NodeSale!$C$9*(1-NodeSale!$C$13)^(B62-1),0) -> 73 | F62: =F61+E62 -> 50000 | G62: =ROUNDUP(D62*F62*(NodeSale!$C$4/NodeSale!$C$3)/NodeSale!$C$9,0) -> 3500000000 | H62: =D62*E62 -> 1022000

Sheet Charts
B2: Public | C2: 0.02
B3: Community | C3: 0.49
B4: Early Stage & Private Investments | C4: 0.1
B5: Liquidity | C5: 0.1
B6: Team, Advisors, Reserve | C6: 0.29
B25: Month | C25: Public Sale | D25: Community Rewards, Marketing & Partnerships | E25: Reserve | F25: Pre Sale | G25: Core Team & Advisors | H25: Liquidity
B26: 46204 | C26: ='Token Release Schedule'!D9 -> 20000000 | D26: =SUM('Token Release Schedule'!I9:L9) -> 78000000 | E26: ='Token Release Schedule'!H9 -> 0 | F26: ='Token Release Schedule'!C9 -> 10000000 | G26: =SUM('Token Release Schedule'!F9:G9) -> 0 | H26: =SUM('Token Release Schedule'!M9:N9) -> 60000000
B27: =EDATE(B26,6) -> 46388 | C27: {=C26 + SUM(INDEX('Token Release Schedule'!D:D, 10 + 6*(ROW()-27)) : INDEX('Token Release Schedule'!D:D, 15 + 6*(ROW()-27) + 5))} -> 20000000 | D27: {=D26 + SUM( INDEX('Token Release Schedule'!I:L, 10 + 6*(ROW()-27), 1) : INDEX('Token Release Schedule'!I:L, 10 + 6*(ROW()-27) + 5, 4) )} -> 1.2368294e+08 | E27: {=E26 + SUM(INDEX('Token Release Schedule'!H:H, 10 + 6*(ROW()-27)) : INDEX('Token Release Schedule'!H:H, 15 + 6*(ROW()-27)))} -> 2222222.2 | F27: {=F26 + SUM(INDEX('Token Release Schedule'!C:C, 10 + 6*(ROW()-27)) : INDEX('Token Release Schedule'!C:C, 15 + 6*(ROW()-27)))} -> 37000000 | G27: {=G26 + SUM( INDEX('Token Release Schedule'!F:G, 10 + 6*(ROW()-27), 1) : INDEX('Token Release Schedule'!F:G, 10 + 6*(ROW()-27) + 5, 2) )} -> 0 | H27: {=H26 + SUM( INDEX('Token Release Schedule'!M:N, 10 + 6*(ROW()-27), 1) : INDEX('Token Release Schedule'!M:N, 10 + 6*(ROW()-27) + 5, 2) )} -> 66857143
B28: =EDATE(B27,6) -> 46569 | C28: {=C27 + SUM(INDEX('Token Release Schedule'!D:D, 10 + 6*(ROW()-27)) : INDEX('Token Release Schedule'!D:D, 15 + 6*(ROW()-27) + 5))} -> 20000000 | D28: {=D27 + SUM( INDEX('Token Release Schedule'!I:L, 10 + 6*(ROW()-27), 1) : INDEX('Token Release Schedule'!I:L, 10 + 6*(ROW()-27) + 5, 4) )} -> 1.700477e+08 | E28: {=E27 + SUM(INDEX('Token Release Schedule'!H:H, 10 + 6*(ROW()-27)) : INDEX('Token Release Schedule'!H:H, 15 + 6*(ROW()-27)))} -> 15555556 | F28: {=F27 + SUM(INDEX('Token Release Schedule'!C:C, 10 + 6*(ROW()-27)) : INDEX('Token Release Schedule'!C:C, 15 + 6*(ROW()-27)))} -> 64000000 | G28: {=G27 + SUM( INDEX('Token Release Schedule'!F:G, 10 + 6*(ROW()-27), 1) : INDEX('Token Release Schedule'!F:G, 10 + 6*(ROW()-27) + 5, 2) )} -> 5833333.3 | H28: {=H27 + SUM( INDEX('Token Release Schedule'!M:N, 10 + 6*(ROW()-27), 1) : INDEX('Token Release Schedule'!M:N, 10 + 6*(ROW()-27) + 5, 2) )} -> 73714286
B29: =EDATE(B28,6) -> 46753 | C29: {=C28 + SUM(INDEX('Token Release Schedule'!D:D, 10 + 6*(ROW()-27)) : INDEX('Token Release Schedule'!D:D, 15 + 6*(ROW()-27) + 5))} -> 20000000 | D29: {=D28 + SUM( INDEX('Token Release Schedule'!I:L, 10 + 6*(ROW()-27), 1) : INDEX('Token Release Schedule'!I:L, 10 + 6*(ROW()-27) + 5, 4) )} -> 2.1982155e+08 | E29: {=E28 + SUM(INDEX('Token Release Schedule'!H:H, 10 + 6*(ROW()-27)) : INDEX('Token Release Schedule'!H:H, 15 + 6*(ROW()-27)))} -> 28888889 | F29: {=F28 + SUM(INDEX('Token Release Schedule'!C:C, 10 + 6*(ROW()-27)) : INDEX('Token Release Schedule'!C:C, 15 + 6*(ROW()-27)))} -> 91000000 | G29: {=G28 + SUM( INDEX('Token Release Schedule'!F:G, 10 + 6*(ROW()-27), 1) : INDEX('Token Release Schedule'!F:G, 10 + 6*(ROW()-27) + 5, 2) )} -> 40833333 | H29: {=H28 + SUM( INDEX('Token Release Schedule'!M:N, 10 + 6*(ROW()-27), 1) : INDEX('Token Release Schedule'!M:N, 10 + 6*(ROW()-27) + 5, 2) )} -> 80571429
B30: =EDATE(B29,6) -> 46935 | C30: {=C29 + SUM(INDEX('Token Release Schedule'!D:D, 10 + 6*(ROW()-27)) : INDEX('Token Release Schedule'!D:D, 15 + 6*(ROW()-27) + 5))} -> 20000000 | D30: {=D29 + SUM( INDEX('Token Release Schedule'!I:L, 10 + 6*(ROW()-27), 1) : INDEX('Token Release Schedule'!I:L, 10 + 6*(ROW()-27) + 5, 4) )} -> 2.695954e+08 | E30: {=E29 + SUM(INDEX('Token Release Schedule'!H:H, 10 + 6*(ROW()-27)) : INDEX('Token Release Schedule'!H:H, 15 + 6*(ROW()-27)))} -> 42222222 | F30: {=F29 + SUM(INDEX('Token Release Schedule'!C:C, 10 + 6*(ROW()-27)) : INDEX('Token Release Schedule'!C:C, 15 + 6*(ROW()-27)))} -> 100000000 | G30: {=G29 + SUM( INDEX('Token Release Schedule'!F:G, 10 + 6*(ROW()-27), 1) : INDEX('Token Release Schedule'!F:G, 10 + 6*(ROW()-27) + 5, 2) )} -> 75833333 | H30: {=H29 + SUM( INDEX('Token Release Schedule'!M:N, 10 + 6*(ROW()-27), 1) : INDEX('Token Release Schedule'!M:N, 10 + 6*(ROW()-27) + 5, 2) )} -> 87428571
B31: =EDATE(B30,6) -> 47119 | C31: {=C30 + SUM(INDEX('Token Release Schedule'!D:D, 10 + 6*(ROW()-27)) : INDEX('Token Release Schedule'!D:D, 15 + 6*(ROW()-27) + 5))} -> 20000000 | D31: {=D30 + SUM( INDEX('Token Release Schedule'!I:L, 10 + 6*(ROW()-27), 1) : INDEX('Token Release Schedule'!I:L, 10 + 6*(ROW()-27) + 5, 4) )} -> 3.1936925e+08 | E31: {=E30 + SUM(INDEX('Token Release Schedule'!H:H, 10 + 6*(ROW()-27)) : INDEX('Token Release Schedule'!H:H, 15 + 6*(ROW()-27)))} -> 55555556 | F31: {=F30 + SUM(INDEX('Token Release Schedule'!C:C, 10 + 6*(ROW()-27)) : INDEX('Token Release Schedule'!C:C, 15 + 6*(ROW()-27)))} -> 100000000 | G31: {=G30 + SUM( INDEX('Token Release Schedule'!F:G, 10 + 6*(ROW()-27), 1) : INDEX('Token Release Schedule'!F:G, 10 + 6*(ROW()-27) + 5, 2) )} -> 1.1083333e+08 | H31: {=H30 + SUM( INDEX('Token Release Schedule'!M:N, 10 + 6*(ROW()-27), 1) : INDEX('Token Release Schedule'!M:N, 10 + 6*(ROW()-27) + 5, 2) )} -> 94285714
B32: =EDATE(B31,6) -> 47300 | C32: {=C31 + SUM(INDEX('Token Release Schedule'!D:D, 10 + 6*(ROW()-27)) : INDEX('Token Release Schedule'!D:D, 15 + 6*(ROW()-27) + 5))} -> 20000000 | D32: {=D31 + SUM( INDEX('Token Release Schedule'!I:L, 10 + 6*(ROW()-27), 1) : INDEX('Token Release Schedule'!I:L, 10 + 6*(ROW()-27) + 5, 4) )} -> 3.6622881e+08 | E32: {=E31 + SUM(INDEX('Token Release Schedule'!H:H, 10 + 6*(ROW()-27)) : INDEX('Token Release Schedule'!H:H, 15 + 6*(ROW()-27)))} -> 68888889 | F32: {=F31 + SUM(INDEX('Token Release Schedule'!C:C, 10 + 6*(ROW()-27)) : INDEX('Token Release Schedule'!C:C, 15 + 6*(ROW()-27)))} -> 100000000 | G32: {=G31 + SUM( INDEX('Token Release Schedule'!F:G, 10 + 6*(ROW()-27), 1) : INDEX('Token Release Schedule'!F:G, 10 + 6*(ROW()-27) + 5, 2) )} -> 1.4583333e+08 | H32: {=H31 + SUM( INDEX('Token Release Schedule'!M:N, 10 + 6*(ROW()-27), 1) : INDEX('Token Release Schedule'!M:N, 10 + 6*(ROW()-27) + 5, 2) )} -> 100000000
B33: =EDATE(B32,6) -> 47484 | C33: {=C32 + SUM(INDEX('Token Release Schedule'!D:D, 10 + 6*(ROW()-27)) : INDEX('Token Release Schedule'!D:D, 15 + 6*(ROW()-27) + 5))} -> 20000000 | D33: {=D32 + SUM( INDEX('Token Release Schedule'!I:L, 10 + 6*(ROW()-27), 1) : INDEX('Token Release Schedule'!I:L, 10 + 6*(ROW()-27) + 5, 4) )} -> 3.9851695e+08 | E33: {=E32 + SUM(INDEX('Token Release Schedule'!H:H, 10 + 6*(ROW()-27)) : INDEX('Token Release Schedule'!H:H, 15 + 6*(ROW()-27)))} -> 80000000 | F33: {=F32 + SUM(INDEX('Token Release Schedule'!C:C, 10 + 6*(ROW()-27)) : INDEX('Token Release Schedule'!C:C, 15 + 6*(ROW()-27)))} -> 100000000 | G33: {=G32 + SUM( INDEX('Token Release Schedule'!F:G, 10 + 6*(ROW()-27), 1) : INDEX('Token Release Schedule'!F:G, 10 + 6*(ROW()-27) + 5, 2) )} -> 1.8083333e+08 | H33: {=H32 + SUM( INDEX('Token Release Schedule'!M:N, 10 + 6*(ROW()-27), 1) : INDEX('Token Release Schedule'!M:N, 10 + 6*(ROW()-27) + 5, 2) )} -> 100000000
B34: =EDATE(B33,6) -> 47665 | C34: {=C33 + SUM(INDEX('Token Release Schedule'!D:D, 10 + 6*(ROW()-27)) : INDEX('Token Release Schedule'!D:D, 15 + 6*(ROW()-27) + 5))} -> 20000000 | D34: {=D33 + SUM( INDEX('Token Release Schedule'!I:L, 10 + 6*(ROW()-27), 1) : INDEX('Token Release Schedule'!I:L, 10 + 6*(ROW()-27) + 5, 4) )} -> 4.3080508e+08 | E34: {=E33 + SUM(INDEX('Token Release Schedule'!H:H, 10 + 6*(ROW()-27)) : INDEX('Token Release Schedule'!H:H, 15 + 6*(ROW()-27)))} -> 80000000 | F34: {=F33 + SUM(INDEX('Token Release Schedule'!C:C, 10 + 6*(ROW()-27)) : INDEX('Token Release Schedule'!C:C, 15 + 6*(ROW()-27)))} -> 100000000 | G34: {=G33 + SUM( INDEX('Token Release Schedule'!F:G, 10 + 6*(ROW()-27), 1) : INDEX('Token Release Schedule'!F:G, 10 + 6*(ROW()-27) + 5, 2) )} -> 210000000 | H34: {=H33 + SUM( INDEX('Token Release Schedule'!M:N, 10 + 6*(ROW()-27), 1) : INDEX('Token Release Schedule'!M:N, 10 + 6*(ROW()-27) + 5, 2) )} -> 100000000
B35: =EDATE(B34,6) -> 47849 | C35: {=C34 + SUM(INDEX('Token Release Schedule'!D:D, 10 + 6*(ROW()-27)) : INDEX('Token Release Schedule'!D:D, 15 + 6*(ROW()-27) + 5))} -> 20000000 | D35: {=D34 + SUM( INDEX('Token Release Schedule'!I:L, 10 + 6*(ROW()-27), 1) : INDEX('Token Release Schedule'!I:L, 10 + 6*(ROW()-27) + 5, 4) )} -> 4.6309322e+08 | E35: {=E34 + SUM(INDEX('Token Release Schedule'!H:H, 10 + 6*(ROW()-27)) : INDEX('Token Release Schedule'!H:H, 15 + 6*(ROW()-27)))} -> 80000000 | F35: {=F34 + SUM(INDEX('Token Release Schedule'!C:C, 10 + 6*(ROW()-27)) : INDEX('Token Release Schedule'!C:C, 15 + 6*(ROW()-27)))} -> 100000000 | G35: {=G34 + SUM( INDEX('Token Release Schedule'!F:G, 10 + 6*(ROW()-27), 1) : INDEX('Token Release Schedule'!F:G, 10 + 6*(ROW()-27) + 5, 2) )} -> 210000000 | H35: {=H34 + SUM( INDEX('Token Release Schedule'!M:N, 10 + 6*(ROW()-27), 1) : INDEX('Token Release Schedule'!M:N, 10 + 6*(ROW()-27) + 5, 2) )} -> 100000000
B36: =EDATE(B35,6) -> 48030 | C36: {=C35 + SUM(INDEX('Token Release Schedule'!D:D, 10 + 6*(ROW()-27)) : INDEX('Token Release Schedule'!D:D, 15 + 6*(ROW()-27) + 4))} -> 40000000 | D36: {=D35 + SUM( INDEX('Token Release Schedule'!I:L, 10 + 6*(ROW()-27), 1) : INDEX('Token Release Schedule'!I:L, 10 + 6*(ROW()-27) + 4, 4) )} -> 490000000 | E36: {=E35 + SUM(INDEX('Token Release Schedule'!H:H, 10 + 6*(ROW()-27)) : INDEX('Token Release Schedule'!H:H, 15 + 6*(ROW()-27) - 1))} -> 80000000 | F36: {=F35 + SUM(INDEX('Token Release Schedule'!C:C, 10 + 6*(ROW()-27)) : INDEX('Token Release Schedule'!C:C, 15 + 6*(ROW()-27) - 1))} -> 100000000 | G36: {=G35 + SUM( INDEX('Token Release Schedule'!F:G, 10 + 6*(ROW()-27), 1) : INDEX('Token Release Schedule'!F:G, 10 + 6*(ROW()-27) + 4, 2) )} -> 210000000 | H36: {=H35 + SUM( INDEX('Token Release Schedule'!M:N, 10 + 6*(ROW()-27), 1) : INDEX('Token Release Schedule'!M:N, 10 + 6*(ROW()-27) + 4, 2) )} -> 100000000 | K36: {=INDEX('Token Release Schedule'!I:L, 10 +5 + 6*(ROW()-27-1), 4)}

Sheet NodeSale
B2: Parameter | C2: Value
B3: Total Nodes | C3: 50000
B4: Total Supply | C4: 1000000000
B5: Rewards % (unused) | C5: 0.2
B6: Num Tiers | C6: 50
B7: Base ETH Price | C7: 0.15
B8: Final ETH Price | C8: 4
B9: Base Node Qty | C9: 4000
B10: ETH/USD Rate | C10: 3500
B12: Price Growth Rate | C12: =((C8/C7)^(1/(C6-1)))-1 -> 0.06930452
B13: Node Decay Rate (seed) | C13: 0.078712
B15: Total Revenue (USD) | C15: =SUM(Nodes!H13:H62) -> 74530505
B16: Total Nodes (sum of tiers) | C16: =SUM(Nodes!E13:E62) -> 50000
B18: Note:
B19: B11 matches the JS priceGrowthRate formula. B12 is the seed decay rate; you can use Goal Seek/Solver to set B15 (Total Nodes) equal to B2 by changing B12.
